{"id":"cli/update","title":"ng update","contents":"\n<article>\n  \n\n\n<div class=\"breadcrumb\">\n  <script type=\"application/ld+json\">\n    {\n      \"@context\": \"http://schema.org\",\n      \"@type\": \"BreadcrumbList\",\n      \"itemListElement\": [\n        { \"@type\": \"ListItem\", \"position\": 1, \"item\": { \"@id\": \"https://angular.io/cli\", \"name\": \"CLI\" } },\n        { \"@type\": \"ListItem\", \"position\": 2, \"item\": { \"@id\": \"https://angular.io/cli/update\", \"name\": \"update\" } }\n      ]\n    }\n  </script>\n    <a href=\"cli\">CLI</a>\n</div>\n\n  \n<header ng-should-translate=\"\" class=\"cli-header\">\n  <h1 id=\"ng-update\">ng update<a title=\"Link to this heading\" class=\"header-link\" aria-hidden=\"true\" href=\"cli/update#ng-update\"><i class=\"material-icons\">link</i></a></h1>\n</header>\n\n\n  <aio-toc class=\"embedded\"></aio-toc>\n\n  <div class=\"cli-body\">\n    <p>更新你的工作區及其依賴項。請參閱<a href=\"https://update.angular.io/\">https://update.angular.io/</a>。</p>\n\n    \n<code-example hidecopy=\"true\" class=\"api-heading no-auto-link\">\n  ng <span class=\"cli-name\">update</span> [<var>packages..</var>]\n</code-example>\n\n\n\n    \n    <h2 class=\"no-anchor\" id=\"----------mode_edit--code--------描述----\">\n        <div class=\"github-links\">\n  <a href=\"https://github.com/ng-docs/angular-cn/edit/cn/packages/angular/cli/src/commands/update/long-description.md?message=docs%3A%20請簡述你的修改...\" aria-label=\"提供編輯建議\" title=\"提供編輯建議\"><i class=\"material-icons\" aria-hidden=\"true\" role=\"img\">mode_edit</i></a>\n  <a href=\"https://github.com/ng-docs/angular-cn/tree/refs/heads/main/packages/angular/cli/src/commands/update/long-description.md\" aria-label=\"檢視原始碼\" title=\"檢視原始碼\"><i class=\"material-icons\" aria-hidden=\"true\" role=\"img\">code</i></a>\n</div>\n        描述\n    </h2>\n    <p>透過執行以下命令，對核心框架和 CLI 的當前穩定版本執行基本更新。</p>\n<code-example>\n ng update @angular/cli @angular/core\n</code-example>\n<p>要更新到下一個 Beta 版或預發行版本，請使用<code>--next</code>選項。</p>\n<p>要從一個主要版本更新到另一個，請使用以下格式</p>\n<code-example>\nng update @angular/cli@^&lt;major_version&gt; @angular/core@^&lt;major_version&gt;\n</code-example>\n<p>我們建議你始終更新到最新的補丁版本，因為它包含我們自初始主要版本以來發布的修復。例如，使用以下命令獲取最新的 10.xx 版本並用它進行更新。</p>\n<code-example>\n ng update @angular/cli@^10 @angular/core@^10\n</code-example>\n<p>有關更新應用程式的詳細資訊和指導，請參閱互動式<a href=\"https://update.angular.io/\">Angular 更新指南</a>。</p>\n\n    \n\n    \n\n    \n\n<h2 class=\"no-anchor\" id=\"arguments\">引數</h2>\n<table class=\"is-full-width list-table property-table\">\n  <thead>\n    <tr>\n      <th style=\"width:15%\">引數</th>\n      <th style=\"width:40%\">說明</th>\n      <th>值型別</th>\n    </tr>\n  </thead>\n  <tbody>\n  \n  <tr class=\"cli-option\">\n    <td><code class=\"cli-option-syntax no-auto-link\">packages</code></td>\n    <td>\n      <p>要更新的套件名稱（可以有多個）。</p>\n\n    </td>\n    <td><code class=\"cli-option-syntax no-auto-link\">string</code></td>\n  </tr>\n  \n  </tbody>\n</table>\n\n\n    \n\n<h2 class=\"no-anchor\" id=\"options\">選項</h2>\n<table class=\"is-full-width list-table property-table\">\n  <thead>\n  <tr>\n    <th style=\"width:15%\">選項</th>\n    <th style=\"width:40%\">說明</th>\n    <th>值型別</th>\n    <th>預設值</th>\n  </tr>\n  </thead>\n  <tbody>\n  \n  <tr class=\"cli-option\">\n    <td>\n      <code class=\"cli-option-syntax no-auto-link\">--allow-dirty</code>\n    </td>\n    <td>\n      \n      <p>是否允許本儲存庫包含已修改或未追蹤的檔案時進行更新。</p>\n\n      \n    </td>\n    <td><code class=\"no-auto-link\">boolean</code></td>\n    <td><code class=\"no-auto-link\">false</code></td>\n  </tr>\n  \n  <tr class=\"cli-option\">\n    <td>\n      <code class=\"cli-option-syntax no-auto-link\">--create-commits</code>\n    </td>\n    <td>\n      \n      <p>為升級和遷移的過程，在原始碼控制中建立一些提交。</p>\n\n      <p><span class=\"cli-aliases\">別名:</span> -C</p>\n    </td>\n    <td><code class=\"no-auto-link\">boolean</code></td>\n    <td><code class=\"no-auto-link\">false</code></td>\n  </tr>\n  \n  <tr class=\"cli-option\">\n    <td>\n      <code class=\"cli-option-syntax no-auto-link\">--force</code>\n    </td>\n    <td>\n      \n      <p>忽略對等依賴版本不匹配的情況。</p>\n\n      \n    </td>\n    <td><code class=\"no-auto-link\">boolean</code></td>\n    <td><code class=\"no-auto-link\">false</code></td>\n  </tr>\n  \n  <tr class=\"cli-option\">\n    <td>\n      <code class=\"cli-option-syntax no-auto-link\">--from</code>\n    </td>\n    <td>\n      \n      <p>要從中遷移的版本。僅適用於要更新的單個套件，並且僅適用於 <code>migrate-only</code>。</p>\n\n      \n    </td>\n    <td><code class=\"no-auto-link\">string</code></td>\n    <td></td>\n  </tr>\n  \n  <tr class=\"cli-option\">\n    <td>\n      <code class=\"cli-option-syntax no-auto-link\">--help</code>\n    </td>\n    <td>\n      \n      <p>在控制檯顯示關於本命令的幫助資訊。</p>\n\n      \n    </td>\n    <td><code class=\"no-auto-link\">boolean</code></td>\n    <td></td>\n  </tr>\n  \n  <tr class=\"cli-option\">\n    <td>\n      <code class=\"cli-option-syntax no-auto-link\">--migrate-only</code>\n    </td>\n    <td>\n      \n      <p>只執行遷移，而不更新已安裝的版本。</p>\n\n      \n    </td>\n    <td><code class=\"no-auto-link\">boolean</code></td>\n    <td></td>\n  </tr>\n  \n  <tr class=\"cli-option\">\n    <td>\n      <code class=\"cli-option-syntax no-auto-link\">--name</code>\n    </td>\n    <td>\n      \n      <p>要執行的遷移的名稱。僅適用於要更新的單個套件，並且僅使用 <code>migrate-only</code> 選項。</p>\n\n      \n    </td>\n    <td><code class=\"no-auto-link\">string</code></td>\n    <td></td>\n  </tr>\n  \n  <tr class=\"cli-option\">\n    <td>\n      <code class=\"cli-option-syntax no-auto-link\">--next</code>\n    </td>\n    <td>\n      \n      <p>使用與釋出版本，包括 beta 和 RC。</p>\n\n      \n    </td>\n    <td><code class=\"no-auto-link\">boolean</code></td>\n    <td><code class=\"no-auto-link\">false</code></td>\n  </tr>\n  \n  <tr class=\"cli-option\">\n    <td>\n      <code class=\"cli-option-syntax no-auto-link\">--to</code>\n    </td>\n    <td>\n      \n      <p>要應用遷移的版本。僅適用於要更新的單個套件，並且僅使用 <code>migrate-only</code> 選項。需要指定 <code>from</code>。預設為檢測到的已安裝版本。</p>\n\n      \n    </td>\n    <td><code class=\"no-auto-link\">string</code></td>\n    <td></td>\n  </tr>\n  \n  <tr class=\"cli-option\">\n    <td>\n      <code class=\"cli-option-syntax no-auto-link\">--verbose</code>\n    </td>\n    <td>\n      \n      <p>在執行期間顯示內部操作的詳細資訊。</p>\n\n      \n    </td>\n    <td><code class=\"no-auto-link\">boolean</code></td>\n    <td><code class=\"no-auto-link\">false</code></td>\n  </tr>\n  \n  </tbody>\n</table>\n\n\n    \n  </div>\n</article>\n\n<!-- links to this doc:\n - cli\n - guide/deprecations\n - guide/updating\n - guide/using-libraries\n-->\n<!-- links from this doc:\n - cli\n - cli/update#ng-update\n - https://github.com/ng-docs/angular-cn/edit/cn/packages/angular/cli/src/commands/update/long-description.md?message=docs%3A%20請簡述你的修改...\n - https://github.com/ng-docs/angular-cn/tree/refs/heads/main/packages/angular/cli/src/commands/update/long-description.md\n - https://update.angular.io/\n-->"}